diran/__init__.py
diran/__main__.py
diran/file_utils.py
diran-1.1.dist-info/METADATA
diran-1.1.dist-info/WHEEL
diran-1.1.dist-info/entry_points.txt
diran-1.1.dist-info/top_level.txt
diran-1.1.dist-info/zip-safe
diran-1.1.dist-info/RECORD
