Metadata-Version: 2.1
Name: diran
Version: 1.1
Summary: 搜索并分析你的文件夹
Home-page: UNKNOWN
Author: Dmeng
Author-email: ecodemo520@outlook.com
License: GPLv3
Platform: UNKNOWN
Requires-Python: >=3
Requires-Dist: prettytable (>=2.1.0)
